README.rst
setup.cfg
setup.py
gribdoctor/__init__.py
gribdoctor.egg-info/PKG-INFO
gribdoctor.egg-info/SOURCES.txt
gribdoctor.egg-info/dependency_links.txt
gribdoctor.egg-info/entry_points.txt
gribdoctor.egg-info/not-zip-safe
gribdoctor.egg-info/requires.txt
gribdoctor.egg-info/top_level.txt
gribdoctor/scripts/__init__.py
gribdoctor/scripts/cli.py
gribdoctor/scripts/cut_splice_globewrap.py