Metadata-Version: 1.0
Name: gribdoctor
Version: 0.1.0dev
Summary: Utility functions for handling grib2s
Home-page: https://github.com/mapbox/grib-doctor
Author: Damon Burgett
Author-email: damon@mapbox.com
License: MIT
Platform: UNKNOWN
